.gitignore
CODE_OF_CONDUCT.md
CONTRIBUTING.md
LICENSE
MANIFEST.in
README.md
environment.yml
requirements.txt
setup.cfg
setup.py
./seqlogo/__init__.py
./seqlogo/core.py
./seqlogo/seqlogo.py
./seqlogo/utils.py
./seqlogo/tests/__init__.py
./seqlogo/tests/test_seqlogo.py
.github/ISSUE_TEMPLATE/bug_report.md
.github/ISSUE_TEMPLATE/feature_request.md
docs/figures/ic_scale.svg
docs/figures/no_ic_scale.svg
seqlogo/__init__.py
seqlogo/core.py
seqlogo/seqlogo.py
seqlogo/utils.py
seqlogo.egg-info/PKG-INFO
seqlogo.egg-info/SOURCES.txt
seqlogo.egg-info/dependency_links.txt
seqlogo.egg-info/not-zip-safe
seqlogo.egg-info/requires.txt
seqlogo.egg-info/top_level.txt
seqlogo/tests/__init__.py
seqlogo/tests/test_seqlogo.py