Metadata-Version: 2.1
Name: seqlogo
Version: 5.29.7
Summary: Python port of the R Bioconductor `seqlogo` package 
Home-page: https://github.com/betteridiot/seqlogo
Author: Marcus D. Sherman
Author-email: mdsherman@betteridiot.tech
License: BSD 3-Clause
Keywords: sequence logo seqlogo bioinformatics genomics weblogo
Platform: UNKNOWN
Classifier: Development Status :: 4 - Beta
Classifier: Intended Audience :: Developers
Classifier: Intended Audience :: End Users/Desktop
Classifier: Intended Audience :: Science/Research
Classifier: Intended Audience :: Information Technology
Classifier: License :: OSI Approved :: BSD License
Classifier: Natural Language :: English
Classifier: Operating System :: Unix
Classifier: Operating System :: MacOS
Classifier: Programming Language :: Python :: 3.5
Classifier: Programming Language :: Python :: 3.5
Classifier: Programming Language :: Python :: 3.6
Classifier: Programming Language :: Python :: 3.7
Classifier: Programming Language :: Python :: Implementation :: CPython
Classifier: Topic :: Scientific/Engineering
Classifier: Topic :: Scientific/Engineering :: Information Analysis
